{
  "pluginName": "AI语音输入法",
  "description": "调用大模型进行语音识别和处理，支持Gemini、通义千问和硅基流动 TeleSpeechASR",
  "version": "1.0.0",
  "author": "余汉波",
  "main": "index.html",
  "logo": "logo.ico",
  "preload": "preload.js",
  "features": [
    {
      "code": "speech-config",
      "explain": "语音输入法设置",
      "description": "配置模型API Key和提示词",
      "cmds": ["语音输入", "Voice Input", "Speech", "AI语音"],
      "icon": "logo.ico",
      "platform": ["win32", "darwin", "linux"],
      "mode": "none",
      "superPanel": true,
      "priority": 10
    }
  ],
  "pluginSetting": {
    "width": 800,
    "height": 600,
    "single": true,
    "autoHideMenuBar": true
  }
}
